chrome_component_downloader/__init__.py
chrome_component_downloader/__main__.py
chrome_component_downloader/chromium_components.py
chrome_component_downloader/errors.py
chrome_component_downloader/update_request.py
chrome_component_downloader-0.1.3.dist-info/LICENSE
chrome_component_downloader-0.1.3.dist-info/METADATA
chrome_component_downloader-0.1.3.dist-info/WHEEL
chrome_component_downloader-0.1.3.dist-info/entry_points.txt
chrome_component_downloader-0.1.3.dist-info/RECORD
