Metadata-Version: 2.3
Name: chrome-component-downloader
Version: 0.1.3
Summary: A Python module and CLI tool to manually download Chrome/Chromium components.
License: MIT
Author: Alberto Verna
Author-email: alberto.verna@hotmail.com
Requires-Python: >=3.9
Classifier: License :: OSI Approved :: MIT License
Classifier: Programming Language :: Python :: 3
Classifier: Programming Language :: Python :: 3.9
Classifier: Programming Language :: Python :: 3.10
Classifier: Programming Language :: Python :: 3.11
Classifier: Programming Language :: Python :: 3.12
Classifier: Programming Language :: Python :: 3.13
Requires-Dist: psutil (>=7.0.0)
Requires-Dist: requests (>=2.32.3)
